sqs_extended_client/__init__.py
sqs_extended_client/client.py
sqs_extended_client/exception_messages.py
sqs_extended_client/exceptions.py
sqs_extended_client/py.typed
amazon_sqs_extended_client-1.0.1.dist-info/LICENSE
amazon_sqs_extended_client-1.0.1.dist-info/METADATA
amazon_sqs_extended_client-1.0.1.dist-info/NOTICE
amazon_sqs_extended_client-1.0.1.dist-info/WHEEL
amazon_sqs_extended_client-1.0.1.dist-info/RECORD
