Metadata-Version: 2.1
Name: amazon-sqs-extended-client
Version: 1.0.1
Summary: Python version of AWS SQS extended client
Home-page: https://github.com/awslabs/amazon-sqs-python-extended-client-lib
License: Apache-2.0
Author: Amazon Web Service - SQS
Requires-Python: >=3.7,<4.0
Classifier: Development Status :: 5 - Production/Stable
Classifier: Intended Audience :: Developers
Classifier: License :: OSI Approved :: Apache Software License
Classifier: Programming Language :: Python :: 3
Classifier: Programming Language :: Python :: 3.7
Classifier: Programming Language :: Python :: 3.8
Classifier: Programming Language :: Python :: 3.9
Classifier: Programming Language :: Python :: 3.10
Classifier: Programming Language :: Python :: 3.11
Classifier: Programming Language :: Python :: 3.12
Requires-Dist: boto3 (>=1.26.91,<2.0.0)
Project-URL: Repository, https://github.com/awslabs/amazon-sqs-python-extended-client-lib
